AUTHORS
CHANGES
INSTALL
LICENCE
MANIFEST.in
README.rst
setup.cfg
setup.py
django_geoportail.egg-info/PKG-INFO
django_geoportail.egg-info/SOURCES.txt
django_geoportail.egg-info/dependency_links.txt
django_geoportail.egg-info/not-zip-safe
django_geoportail.egg-info/top_level.txt
docs/Makefile
docs/source/admin.rst
docs/source/conf.py
docs/source/forms.rst
docs/source/index.rst
docs/source/installation.rst
docs/source/settings.rst
docs/source/templates.rst
docs/source/img/admin-default.png
docs/source/img/admin.png
docs/source/img/example.png
docs/source/img/geoportal.png
docs/source/img/template-custom.png
docs/source/img/template-green.png
docs/source/img/template.png
docs/source/themes/nature/theme.conf
docs/source/themes/nature/static/nature.css_t
examples/__init__.py
examples/manage.py
examples/settings.py
examples/urls.py
examples/geoportal/__init__.py
examples/geoportal/admin.py
examples/geoportal/models.py
examples/geoportal/tests.py
examples/geoportal/utils.py
examples/geoportal/forms/__init__.py
examples/geoportal/forms/fields.py
examples/geoportal/forms/widgets.py
examples/geoportal/templatetags/__init__.py
examples/geoportal/templatetags/geoportal_tags.py
geoportal/__init__.py
geoportal/admin.py
geoportal/models.py
geoportal/tests.py
geoportal/utils.py
geoportal/forms/__init__.py
geoportal/forms/fields.py
geoportal/forms/widgets.py
geoportal/templates/geoportal/gml.html
geoportal/templates/geoportal/map.html
geoportal/templates/geoportal/widget.html
geoportal/templates/gis/admin/geoportal.html
geoportal/templates/gis/admin/geoportal.js
geoportal/templatetags/__init__.py
geoportal/templatetags/geoportal_tags.py