Metadata-Version: 1.0
Name: django-geoportail
Version: 0.4.6
Summary: Add maps and photos from the French National Geographic Institute to GeoDjango
Home-page: http://bitbucket.org/bruno/django-geoportail
Author: Bruno Renie
Author-email: bruno@renie.fr
License: BSD licence, see LICENCE file
Platform: UNKNOWN
Classifier: Development Status :: 3 - Alpha
Classifier: Environment :: Web Environment
Classifier: Framework :: Django
Classifier: Intended Audience :: Developers
Classifier: License :: OSI Approved :: BSD License
Classifier: Natural Language :: English
Classifier: Programming Language :: Python
Classifier: Programming Language :: JavaScript
Classifier: Topic :: Scientific/Engineering :: GIS
